epyr/__init__.py
epyr/cli.py
epyr/config.py
epyr/eprload.py
epyr/eprplot.py
epyr/isotope_gui.py
epyr/logging_config.py
epyr/performance.py
epyr/plugins.py
epyr/baseline/__init__.py
epyr/baseline/auto.py
epyr/baseline/correction.py
epyr/baseline/interactive.py
epyr/baseline/models.py
epyr/baseline/selection.py
epyr/fair/__init__.py
epyr/fair/conversion.py
epyr/fair/data_processing.py
epyr/fair/exporters.py
epyr/fair/parameter_mapping.py
epyr/fair/validation.py
epyr/lineshapes/__init__.py
epyr/lineshapes/convspec.py
epyr/lineshapes/fitting.py
epyr/lineshapes/gaussian.py
epyr/lineshapes/lineshape_class.py
epyr/lineshapes/lorentzian.py
epyr/lineshapes/lshape.py
epyr/lineshapes/voigtian.py
epyr/physics/__init__.py
epyr/physics/constants.py
epyr/physics/conversions.py
epyr/physics/units.py
epyr/signalprocessing/__init__.py
epyr/signalprocessing/apowin.py
epyr/signalprocessing/frequency_analysis.py
epyr/sub/__init__.py
epyr/sub/isotopedata.txt
epyr/sub/loadBES3T.py
epyr/sub/loadESP.py
epyr/sub/utils.py
epyr_tools-0.3.1.dist-info/licenses/LICENSE
epyr_tools-0.3.1.dist-info/METADATA
epyr_tools-0.3.1.dist-info/WHEEL
epyr_tools-0.3.1.dist-info/entry_points.txt
epyr_tools-0.3.1.dist-info/top_level.txt
epyr_tools-0.3.1.dist-info/RECORD
